pydref_serializers/__init__.py
pydref_serializers/builders.py
pydref_serializers/getters.py
pydref_serializers/mappers/__init__.py
pydref_serializers/mappers/fields.py
pydref_serializers/mappers/validators.py
pydref_serializers/serializers.py
pydref_serializers-0.2.4.dist-info/METADATA
pydref_serializers-0.2.4.dist-info/WHEEL
pydref_serializers-0.2.4.dist-info/RECORD
